dtige/__cli__.py
dtige/__init__.py
dtige/_version.py
dtige/conf/__init__.py
dtige/conf/about/dtige.yaml
dtige/py.typed
dtige-0.1.0.dist-info/LICENSE
dtige-0.1.0.dist-info/METADATA
dtige-0.1.0.dist-info/WHEEL
dtige-0.1.0.dist-info/entry_points.txt
dtige-0.1.0.dist-info/RECORD
